CHANGELOG.rst
INSTALL.rst
LICENSE
MANIFEST.in
README.rst
setup.cfg
setup.py
versioneer.py
bayespy/__init__.py
bayespy/_meta.py
bayespy/_version.py
bayespy/discrete_example.py
bayespy/plot.py
bayespy/testing.py
bayespy.egg-info/PKG-INFO
bayespy.egg-info/SOURCES.txt
bayespy.egg-info/dependency_links.txt
bayespy.egg-info/entry_points.txt
bayespy.egg-info/requires.txt
bayespy.egg-info/top_level.txt
bayespy/demos/__init__.py
bayespy/demos/annealing.py
bayespy/demos/black_box.py
bayespy/demos/categorical.py
bayespy/demos/collapsed_cg.py
bayespy/demos/gamma_shape.py
bayespy/demos/hmm.py
bayespy/demos/lda.py
bayespy/demos/lssm.py
bayespy/demos/lssm_sd.py
bayespy/demos/lssm_tvd.py
bayespy/demos/mog.py
bayespy/demos/pattern_search.py
bayespy/demos/pca.py
bayespy/demos/saving.py
bayespy/demos/stochastic_inference.py
bayespy/inference/__init__.py
bayespy/inference/vmp/__init__.py
bayespy/inference/vmp/transformations.py
bayespy/inference/vmp/vmp.py
bayespy/inference/vmp/nodes/CovarianceFunctions.py
bayespy/inference/vmp/nodes/GaussianProcesses.py
bayespy/inference/vmp/nodes/__init__.py
bayespy/inference/vmp/nodes/add.py
bayespy/inference/vmp/nodes/bernoulli.py
bayespy/inference/vmp/nodes/beta.py
bayespy/inference/vmp/nodes/binomial.py
bayespy/inference/vmp/nodes/categorical.py
bayespy/inference/vmp/nodes/categorical_markov_chain.py
bayespy/inference/vmp/nodes/concat_gaussian.py
bayespy/inference/vmp/nodes/concatenate.py
bayespy/inference/vmp/nodes/constant.py
bayespy/inference/vmp/nodes/converters.py
bayespy/inference/vmp/nodes/deterministic.py
bayespy/inference/vmp/nodes/dirichlet.py
bayespy/inference/vmp/nodes/dot.py
bayespy/inference/vmp/nodes/expfamily.py
bayespy/inference/vmp/nodes/exponential.py
bayespy/inference/vmp/nodes/gamma.py
bayespy/inference/vmp/nodes/gate.py
bayespy/inference/vmp/nodes/gaussian.py
bayespy/inference/vmp/nodes/gaussian_markov_chain.py
bayespy/inference/vmp/nodes/gp.py
bayespy/inference/vmp/nodes/logistic.py
bayespy/inference/vmp/nodes/logpdf.py
bayespy/inference/vmp/nodes/mixture.py
bayespy/inference/vmp/nodes/ml.py
bayespy/inference/vmp/nodes/multinomial.py
bayespy/inference/vmp/nodes/node.py
