Metadata-Version: 2.1
Name: bayespy
Version: 0.5.26
Summary: Variational Bayesian inference tools for Python
Home-page: http://bayespy.org
Author: Jaakko Luttinen
Author-email: jaakko.luttinen@iki.fi
License: UNKNOWN
Keywords: variational Bayes,probabilistic programming,Bayesian networks,graphical models,variational message passing
Platform: UNKNOWN
Classifier: Programming Language :: Python :: 3 :: Only
Classifier: Programming Language :: Python :: 3.3
Classifier: Programming Language :: Python :: 3.4
Classifier: Development Status :: 4 - Beta
Classifier: Environment :: Console
Classifier: Intended Audience :: Developers
Classifier: Intended Audience :: Science/Research
Classifier: License :: OSI Approved :: MIT License
Classifier: Operating System :: OS Independent
Classifier: Topic :: Scientific/Engineering
Classifier: Topic :: Scientific/Engineering :: Information Analysis
Provides-Extra: doc
Provides-Extra: dev
